unimoji/__init__.py
unimoji/__main__.py
unimoji/codes.json
unimoji/main.py
unimoji-2.0.0.dist-info/licenses/LICENSE
unimoji-2.0.0.dist-info/METADATA
unimoji-2.0.0.dist-info/WHEEL
unimoji-2.0.0.dist-info/entry_points.txt
unimoji-2.0.0.dist-info/top_level.txt
unimoji-2.0.0.dist-info/RECORD
