Metadata-Version: 2.4
Name: unimoji
Version: 2.0.0
Summary: Accurately remove and replace emojis in text strings
Home-page: https://github.com/pxawtyy/unimoji
Author: Michael Kuwahara
Author-email: prod.samiichy@gmail.com
License: Apache-2.0
Project-URL: Source, https://github.com/pxawtyy/unimoji
Project-URL: Documentation, https://github.com/pxawtyy/unimoji/blob/master/README.md
Project-URL: Bug Reports, https://github.com/pxawtyy/unimoji/issues
Keywords: emoji,emojis,nlp,natural langauge processing,unicode,unicode-emoji
Classifier: Development Status :: 4 - Beta
Classifier: Topic :: Utilities
Classifier: Topic :: Text Processing
Classifier: License :: OSI Approved :: Apache Software License
Classifier: Programming Language :: Python :: 3
Classifier: Programming Language :: Python :: 3 :: Only
Classifier: Programming Language :: Python :: 3.8
Classifier: Programming Language :: Python :: 3.9
Classifier: Programming Language :: Python :: 3.10
Classifier: Programming Language :: Python :: 3.11
Classifier: Programming Language :: Python :: 3.12
Classifier: Programming Language :: Python :: 3.13
Classifier: Programming Language :: Python :: Implementation :: CPython
Requires-Python: >=3.8
License-File: LICENSE
Provides-Extra: ujson
Requires-Dist: ujson; extra == "ujson"
Dynamic: license-file
